pyeasyga/__init__.py
pyeasyga/pyeasyga.py
pyeasyga-0.3.0.dist-info/DESCRIPTION.rst
pyeasyga-0.3.0.dist-info/METADATA
pyeasyga-0.3.0.dist-info/metadata.json
pyeasyga-0.3.0.dist-info/RECORD
pyeasyga-0.3.0.dist-info/top_level.txt
pyeasyga-0.3.0.dist-info/WHEEL
