Metadata-Version: 2.0
Name: pyeasyga
Version: 0.3.0
Summary: A simple and easy-to-use Genetic Algorithm implementation library in Python
Home-page: https://github.com/remiomosowon/pyeasyga
Author: Ayodeji Remi-Omosowon
Author-email: remiomosowon@gmail.com
License: BSD
Keywords: pyeasyga
Platform: UNKNOWN
Classifier: Development Status :: 3 - Alpha
Classifier: Intended Audience :: Developers
Classifier: License :: OSI Approved :: BSD License
Classifier: Natural Language :: English
Classifier: Operating System :: OS Independent
Classifier: Programming Language :: Python :: 2
Classifier: Programming Language :: Python :: 2.6
Classifier: Programming Language :: Python :: 2.7
Classifier: Programming Language :: Python :: 3
Classifier: Programming Language :: Python :: 3.4
Classifier: Topic :: Scientific/Engineering :: Artificial Intelligence
Requires-Dist: six
